napari_layer_table/__init__.py
napari_layer_table/_data_model.py
napari_layer_table/_my_layer.py
napari_layer_table/_my_logger.py
napari_layer_table/_my_widget.py
napari_layer_table/_table_widget.py
napari_layer_table/_undo.py
napari_layer_table/debugInterface.py
napari_layer_table/napari.yaml
napari_layer_table/_tests/__init__.py
napari_layer_table/_tests/test_myTableView.py
napari_layer_table/_tests/test_my_logger.py
napari_layer_table/_tests/test_my_widget.py
napari_layer_table/_tests/test_pandas_model.py
napari_layer_table-0.0.13.dist-info/LICENSE
napari_layer_table-0.0.13.dist-info/METADATA
napari_layer_table-0.0.13.dist-info/WHEEL
napari_layer_table-0.0.13.dist-info/entry_points.txt
napari_layer_table-0.0.13.dist-info/top_level.txt
napari_layer_table-0.0.13.dist-info/RECORD
