Metadata-Version: 2.1
Name: napari-layer-table
Version: 0.0.13
Summary: A plugin to display a layer as a table.
Home-page: https://github.com/mapmanager/napari-layer-table
Author: Robert Cudmore
Author-email: rhcudmore@ucdavis.edu
License: GPL-3.0-only
Project-URL: Bug Tracker, https://github.com/mapmanager/napari-layer-table/issues
Project-URL: Documentation, https://github.com/mapmanager/napari-layer-table#README.md
Project-URL: Source Code, https://github.com/mapmanager/napari-layer-table
Project-URL: User Support, https://github.com/mapmanager/napari-layer-table/issues
Classifier: Development Status :: 2 - Pre-Alpha
Classifier: Intended Audience :: Developers
Classifier: Framework :: napari
Classifier: Topic :: Software Development :: Testing
Classifier: Programming Language :: Python
Classifier: Programming Language :: Python :: 3.9
Classifier: Programming Language :: Python :: 3.10
Classifier: Programming Language :: Python :: 3.11
Classifier: Operating System :: OS Independent
Classifier: License :: OSI Approved :: GNU General Public License v3 (GPLv3)
Requires-Python: >=3.9
License-File: LICENSE
Requires-Dist: numpy
